data_mock/google/cloud/__init__.py
data_mock/google/cloud/client.py
data_mock/google/cloud/exceptions.py
data_mock/google/cloud/schema.py
data_mock/google/cloud/table.py
py_bigquery_mock-0.2.4.data/scripts/mkmock.py
py_bigquery_mock-0.2.4.dist-info/LICENSE
py_bigquery_mock-0.2.4.dist-info/METADATA
py_bigquery_mock-0.2.4.dist-info/WHEEL
py_bigquery_mock-0.2.4.dist-info/top_level.txt
py_bigquery_mock-0.2.4.dist-info/RECORD
