Metadata-Version: 2.1
Name: py-bigquery-mock
Version: 0.2.4
Summary: Mock BigQuery
Home-page: https://github.com/paulhtremblay/py-bigquery-mock
Author: Henry Tremblay
Author-email: paulhtremblay@gmail.com
License: GNU GENERAL PUBLIC LICENSE
Classifier: Programming Language :: Python :: 3
License-File: LICENSE
